{"name":"World Cuppo - Finalo Solutiono","count":73,"frequency":"hourly","version":500,"newdata":true,"lastrunstatus":"success","lastsuccess":"Sun Jul 06 2014 23:00:18 GMT+0000 (UTC)","nextrun":"Mon Jul 07 2014 00:00:18 GMT+0000 (UTC)","results":{"collection1":[{"hometeam":{"text":"Brazil","href":"http://en.wikipedia.org/wiki/Brazil_national_football_team"},"homescorers":[{"text":"Neymar","href":"http://en.wikipedia.org/wiki/Neymar"},{"text":"Oscar","href":"http://en.wikipedia.org/wiki/Oscar_(footballer,_born_1991)"}],"awayteam":{"text":"Croatia","href":"http://en.wikipedia.org/wiki/Croatia_national_football_team"},"awayscorers":{"text":"Marcelo","href":"http://en.wikipedia.org/wiki/Marcelo_Vieira"},"scoreline":"3–1"},{"hometeam":{"text":"Mexico","href":"http://en.wikipedia.org/wiki/Mexico_national_football_team"},"homescorers":{"text":"Peralta","href":"http://en.wikipedia.org/wiki/Oribe_Peralta"},"awayteam":{"text":"Cameroon","href":"http://en.wikipedia.org/wiki/Cameroon_national_football_team"},"awayscorers":"","scoreline":"1–0"},{"hometeam":{"text":"Brazil","href":"http://en.wikipedia.org/wiki/Brazil_national_football_team"},"homescorers":"","awayteam":{"text":"Mexico","href":"http://en.wikipedia.org/wiki/Mexico_national_football_team"},"awayscorers":"","scoreline":"0–0"},{"hometeam":{"text":"Cameroon","href":"http://en.wikipedia.org/wiki/Cameroon_national_football_team"},"homescorers":"","awayteam":{"text":"Croatia","href":"http://en.wikipedia.org/wiki/Croatia_national_football_team"},"awayscorers":[{"text":"Olić","href":"http://en.wikipedia.org/wiki/Ivica_Oli%C4%87"},{"text":"Perišić","href":"http://en.wikipedia.org/wiki/Ivan_Peri%C5%A1i%C4%87"},{"text":"Mandžukić","href":"http://en.wikipedia.org/wiki/Mario_Mand%C5%BEuki%C4%87"}],"scoreline":"0–4"},{"hometeam":{"text":"Cameroon","href":"http://en.wikipedia.org/wiki/Cameroon_national_football_team"},"homescorers":{"text":"Matip","href":"http://en.wikipedia.org/wiki/Jo%C3%ABl_Matip"},"awayteam":{"text":"Brazil","href":"http://en.wikipedia.org/wiki/Brazil_national_football_team"},"awayscorers":[{"text":"Neymar","href":"http://en.wikipedia.org/wiki/Neymar"},{"text":"Fred","href":"http://en.wikipedia.org/wiki/Fred_(footballer)"},{"text":"Fernandinho","href":"http://en.wikipedia.org/wiki/Fernando_Luiz_Roza"}],"scoreline":"1–4"},{"hometeam":{"text":"Croatia","href":"http://en.wikipedia.org/wiki/Croatia_national_football_team"},"homescorers":{"text":"Perišić","href":"http://en.wikipedia.org/wiki/Ivan_Peri%C5%A1i%C4%87"},"awayteam":{"text":"Mexico","href":"http://en.wikipedia.org/wiki/Mexico_national_football_team"},"awayscorers":[{"text":"Márquez","href":"http://en.wikipedia.org/wiki/Rafael_M%C3%A1rquez"},{"text":"Guardado","href":"http://en.wikipedia.org/wiki/Andr%C3%A9s_Guardado"},{"text":"Hernández","href":"http://en.wikipedia.org/wiki/Javier_Hern%C3%A1ndez_Balc%C3%A1zar"}],"scoreline":"1–3"},{"hometeam":"","homescorers":"","awayteam":"","awayscorers":"","scoreline":""},{"hometeam":"","homescorers":"","awayteam":"","awayscorers":"","scoreline":""},{"hometeam":"","homescorers":"","awayteam":"","awayscorers":"","scoreline":""},{"hometeam":"","homescorers":"","awayteam":"","awayscorers":"","scoreline":""},{"hometeam":{"text":"Spain","href":"http://en.wikipedia.org/wiki/Spain_national_football_team"},"homescorers":{"text":"Alonso","href":"http://en.wikipedia.org/wiki/Xabi_Alonso"},"awayteam":{"text":"Netherlands","href":"http://en.wikipedia.org/wiki/Netherlands_national_football_team"},"awayscorers":[{"text":"Van Persie","href":"http://en.wikipedia.org/wiki/Robin_van_Persie"},{"text":"Robben","href":"http://en.wikipedia.org/wiki/Arjen_Robben"},{"text":"De Vrij","href":"http://en.wikipedia.org/wiki/Stefan_de_Vrij"}],"scoreline":"1–5"},{"hometeam":{"text":"Chile","href":"http://en.wikipedia.org/wiki/Chile_national_football_team"},"homescorers":[{"text":"Sánchez","href":"http://en.wikipedia.org/wiki/Alexis_S%C3%A1nchez"},{"text":"Valdivia","href":"http://en.wikipedia.org/wiki/Jorge_Valdivia"},{"text":"Beausejour","href":"http://en.wikipedia.org/wiki/Jean_Beausejour"}],"awayteam":{"text":"Australia","href":"http://en.wikipedia.org/wiki/Australia_national_association_football_team"},"awayscorers":{"text":"Cahill","href":"http://en.wikipedia.org/wiki/Tim_Cahill"},"scoreline":"3–1"},{"hometeam":{"text":"Spain","href":"http://en.wikipedia.org/wiki/Spain_national_football_team"},"homescorers":"","awayteam":{"text":"Chile","href":"http://en.wikipedia.org/wiki/Chile_national_football_team"},"awayscorers":[{"text":"Vargas","href":"http://en.wikipedia.org/wiki/Eduardo_Vargas"},{"text":"Aránguiz","href":"http://en.wikipedia.org/wiki/Charles_Ar%C3%A1nguiz"}],"scoreline":"0–2"},{"hometeam":{"text":"Netherlands","href":"http://en.wikipedia.org/wiki/Netherlands_national_football_team"},"homescorers":[{"text":"Fer","href":"http://en.wikipedia.org/wiki/Leroy_Fer"},{"text":"Memphis","href":"http://en.wikipedia.org/wiki/Memphis_Depay"}],"awayteam":{"text":"Chile","href":"http://en.wikipedia.org/wiki/Chile_national_football_team"},"awayscorers":"","scoreline":"2–0"},{"hometeam":{"text":"Australia","href":"http://en.wikipedia.org/wiki/Australia_national_association_football_team"},"homescorers":[{"text":"Cahill","href":"http://en.wikipedia.org/wiki/Tim_Cahill"},{"text":"Jedinak","href":"http://en.wikipedia.org/wiki/Mile_Jedinak"}],"awayteam":{"text":"Netherlands","href":"http://en.wikipedia.org/wiki/Netherlands_national_football_team"},"awayscorers":[{"text":"Robben","href":"http://en.wikipedia.org/wiki/Arjen_Robben"},{"text":"Van Persie","href":"http://en.wikipedia.org/wiki/Robin_van_Persie"},{"text":"Memphis","href":"http://en.wikipedia.org/wiki/Memphis_Depay"}],"scoreline":"2–3"},{"hometeam":{"text":"Australia","href":"http://en.wikipedia.org/wiki/Australia_national_association_football_team"},"homescorers":"","awayteam":{"text":"Spain","href":"http://en.wikipedia.org/wiki/Spain_national_football_team"},"awayscorers":[{"text":"Villa","href":"http://en.wikipedia.org/wiki/David_Villa"},{"text":"Torres","href":"http://en.wikipedia.org/wiki/Fernando_Torres"},{"text":"Mata","href":"http://en.wikipedia.org/wiki/Juan_Mata"}],"scoreline":"0–3"},{"hometeam":"","homescorers":"","awayteam":"","awayscorers":"","scoreline":""},{"hometeam":"","homescorers":"","awayteam":"","awayscorers":"","scoreline":""},{"hometeam":"","homescorers":"","awayteam":"","awayscorers":"","scoreline":""},{"hometeam":"","homescorers":"","awayteam":"","awayscorers":"","scoreline":""},{"hometeam":"","homescorers":"","awayteam":"","awayscorers":"","scoreline":""},{"hometeam":"","homescorers":"","awayteam":"","awayscorers":"","scoreline":""},{"hometeam":{"text":"Colombia","href":"http://en.wikipedia.org/wiki/Colombia_national_football_team"},"homescorers":[{"text":"Armero","href":"http://en.wikipedia.org/wiki/Pablo_Armero"},{"text":"Gutiérrez","href":"http://en.wikipedia.org/wiki/Te%C3%B3filo_Guti%C3%A9rrez"},{"text":"Rodríguez","href":"http://en.wikipedia.org/wiki/James_Rodr%C3%ADguez"}],"awayteam":{"text":"Greece","href":"http://en.wikipedia.org/wiki/Greece_national_football_team"},"awayscorers":"","scoreline":"3–0"},{"hometeam":{"text":"Japan","href":"http://en.wikipedia.org/wiki/Japan_national_football_team"},"homescorers":"","awayteam":{"text":"Greece","href":"http://en.wikipedia.org/wiki/Greece_national_football_team"},"awayscorers":"","scoreline":"0–0"},{"hometeam":{"text":"Ivory Coast","href":"http://en.wikipedia.org/wiki/Ivory_Coast_national_football_team"},"homescorers":[{"text":"Bony","href":"http://en.wikipedia.org/wiki/Wilfried_Bony"},{"text":"Gervinho","href":"http://en.wikipedia.org/wiki/Gervinho"}],"awayteam":{"text":"Japan","href":"http://en.wikipedia.org/wiki/Japan_national_football_team"},"awayscorers":{"text":"Honda","href":"http://en.wikipedia.org/wiki/Keisuke_Honda"},"scoreline":"2–1"},{"hometeam":{"text":"Colombia","href":"http://en.wikipedia.org/wiki/Colombia_national_football_team"},"homescorers":[{"text":"Rodríguez","href":"http://en.wikipedia.org/wiki/James_Rodr%C3%ADguez"},{"text":"Quintero","href":"http://en.wikipedia.org/wiki/Juan_Fernando_Quintero"}],"awayteam":{"text":"Ivory Coast","href":"http://en.wikipedia.org/wiki/Ivory_Coast_national_football_team"},"awayscorers":{"text":"Gervinho","href":"http://en.wikipedia.org/wiki/Gervinho"},"scoreline":"2–1"},{"hometeam":{"text":"Japan","href":"http://en.wikipedia.org/wiki/Japan_national_football_team"},"homescorers":{"text":"Okazaki","href":"http://en.wikipedia.org/wiki/Shinji_Okazaki"},"awayteam":{"text":"Colombia","href":"http://en.wikipedia.org/wiki/Colombia_national_football_team"},"awayscorers":[{"text":"Cuadrado","href":"http://en.wikipedia.org/wiki/Juan_Guillermo_Cuadrado"},{"text":"Martínez","href":"http://en.wikipedia.org/wiki/Jackson_Mart%C3%ADnez"},{"text":"Rodríguez","href":"http://en.wikipedia.org/wiki/James_Rodr%C3%ADguez"}],"scoreline":"1–4"},{"hometeam":{"text":"Greece","href":"http://en.wikipedia.org/wiki/Greece_national_football_team"},"homescorers":[{"text":"Samaris","href":"http://en.wikipedia.org/wiki/Andreas_Samaris"},{"text":"Samaras","href":"http://en.wikipedia.org/wiki/Georgios_Samaras"}],"awayteam":{"text":"Ivory Coast","href":"http://en.wikipedia.org/wiki/Ivory_Coast_national_football_team"},"awayscorers":{"text":"Bony","href":"http://en.wikipedia.org/wiki/Wilfried_Bony"},"scoreline":"2–1"},{"hometeam":"","homescorers":"","awayteam":"","awayscorers":"","scoreline":""},{"hometeam":"","homescorers":"","awayteam":"","awayscorers":"","scoreline":""},{"hometeam":"","homescorers":"","awayteam":"","awayscorers":"","scoreline":""},{"hometeam":"","homescorers":"","awayteam":"","awayscorers":"","scoreline":""},{"hometeam":{"text":"Uruguay","href":"http://en.wikipedia.org/wiki/Uruguay_national_football_team"},"homescorers":{"text":"Cavani","href":"http://en.wikipedia.org/wiki/Edinson_Cavani"},"awayteam":{"text":"Costa Rica","href":"http://en.wikipedia.org/wiki/Costa_Rica_national_football_team"},"awayscorers":[{"text":"Campbell","href":"http://en.wikipedia.org/wiki/Joel_Campbell"},{"text":"Duarte","href":"http://en.wikipedia.org/wiki/%C3%93scar_Duarte_(Costa_Rican_footballer)"},{"text":"Ureña","href":"http://en.wikipedia.org/wiki/Marco_Ure%C3%B1a"}],"scoreline":"1–3"},{"hometeam":{"text":"England","href":"http://en.wikipedia.org/wiki/England_national_football_team"},"homescorers":{"text":"Sturridge","href":"http://en.wikipedia.org/wiki/Daniel_Sturridge"},"awayteam":{"text":"Italy","href":"http://en.wikipedia.org/wiki/Italy_national_football_team"},"awayscorers":[{"text":"Marchisio","href":"http://en.wikipedia.org/wiki/Claudio_Marchisio"},{"text":"Balotelli","href":"http://en.wikipedia.org/wiki/Mario_Balotelli"}],"scoreline":"1–2"},{"hometeam":{"text":"Uruguay","href":"http://en.wikipedia.org/wiki/Uruguay_national_football_team"},"homescorers":{"text":"Suárez","href":"http://en.wikipedia.org/wiki/Luis_Su%C3%A1rez"},"awayteam":{"text":"England","href":"http://en.wikipedia.org/wiki/England_national_football_team"},"awayscorers":{"text":"Rooney","href":"http://en.wikipedia.org/wiki/Wayne_Rooney"},"scoreline":"2–1"},{"hometeam":{"text":"Costa Rica","href":"http://en.wikipedia.org/wiki/Costa_Rica_national_football_team"},"homescorers":"","awayteam":{"text":"England","href":"http://en.wikipedia.org/wiki/England_national_football_team"},"awayscorers":"","scoreline":"0–0"},{"hometeam":{"text":"Italy","href":"http://en.wikipedia.org/wiki/Italy_national_football_team"},"homescorers":"","awayteam":{"text":"Costa Rica","href":"http://en.wikipedia.org/wiki/Costa_Rica_national_football_team"},"awayscorers":{"text":"Ruiz","href":"http://en.wikipedia.org/wiki/Bryan_Ruiz"},"scoreline":"0–1"},{"hometeam":{"text":"Italy","href":"http://en.wikipedia.org/wiki/Italy_national_football_team"},"homescorers":"","awayteam":{"text":"Uruguay","href":"http://en.wikipedia.org/wiki/Uruguay_national_football_team"},"awayscorers":{"text":"Godín","href":"http://en.wikipedia.org/wiki/Diego_God%C3%ADn"},"scoreline":"0–1"},{"hometeam":"","homescorers":"","awayteam":"","awayscorers":"","scoreline":""},{"hometeam":"","homescorers":"","awayteam":"","awayscorers":"","scoreline":""},{"hometeam":{"text":"Switzerland","href":"http://en.wikipedia.org/wiki/Switzerland_national_football_team"},"homescorers":[{"text":"Mehmedi","href":"http://en.wikipedia.org/wiki/Admir_Mehmedi"},{"text":"Seferović","href":"http://en.wikipedia.org/wiki/Haris_Seferovi%C4%87"}],"awayteam":{"text":"Ecuador","href":"http://en.wikipedia.org/wiki/Ecuador_national_football_team"},"awayscorers":{"text":"E. Valencia","href":"http://en.wikipedia.org/wiki/Enner_Valencia"},"scoreline":"2–1"},{"hometeam":{"text":"France","href":"http://en.wikipedia.org/wiki/France_national_football_team"},"homescorers":[{"text":"Benzema","href":"http://en.wikipedia.org/wiki/Karim_Benzema"},{"text":"Valladares","href":"http://en.wikipedia.org/wiki/Noel_Valladares"}],"awayteam":{"text":"Honduras","href":"http://en.wikipedia.org/wiki/Honduras_national_football_team"},"awayscorers":"","scoreline":"3–0"},{"hometeam":{"text":"Ecuador","href":"http://en.wikipedia.org/wiki/Ecuador_national_football_team"},"homescorers":"","awayteam":{"text":"France","href":"http://en.wikipedia.org/wiki/France_national_football_team"},"awayscorers":"","scoreline":"0–0"},{"hometeam":{"text":"Honduras","href":"http://en.wikipedia.org/wiki/Honduras_national_football_team"},"homescorers":"","awayteam":{"text":"Switzerland","href":"http://en.wikipedia.org/wiki/Switzerland_national_football_team"},"awayscorers":{"text":"Shaqiri","href":"http://en.wikipedia.org/wiki/Xherdan_Shaqiri"},"scoreline":"0–3"},{"hometeam":{"text":"Honduras","href":"http://en.wikipedia.org/wiki/Honduras_national_football_team"},"homescorers":{"text":"Costly","href":"http://en.wikipedia.org/wiki/Carlo_Costly"},"awayteam":{"text":"Ecuador","href":"http://en.wikipedia.org/wiki/Ecuador_national_football_team"},"awayscorers":{"text":"E. Valencia","href":"http://en.wikipedia.org/wiki/Enner_Valencia"},"scoreline":"1–2"},{"hometeam":{"text":"Switzerland","href":"http://en.wikipedia.org/wiki/Switzerland_national_football_team"},"homescorers":[{"text":"Džemaili","href":"http://en.wikipedia.org/wiki/Blerim_D%C5%BEemaili"},{"text":"Xhaka","href":"http://en.wikipedia.org/wiki/Granit_Xhaka"}],"awayteam":{"text":"France","href":"http://en.wikipedia.org/wiki/France_national_football_team"},"awayscorers":[{"text":"Giroud","href":"http://en.wikipedia.org/wiki/Olivier_Giroud"},{"text":"Matuidi","href":"http://en.wikipedia.org/wiki/Blaise_Matuidi"},{"text":"Valbuena","href":"http://en.wikipedia.org/wiki/Mathieu_Valbuena"},{"text":"Benzema","href":"http://en.wikipedia.org/wiki/Karim_Benzema"},{"text":"Sissoko","href":"http://en.wikipedia.org/wiki/Moussa_Sissoko"}],"scoreline":"2–5"},{"hometeam":"","homescorers":"","awayteam":"","awayscorers":"","scoreline":""},{"hometeam":"","homescorers":"","awayteam":"","awayscorers":"","scoreline":""},{"hometeam":{"text":"Iran","href":"http://en.wikipedia.org/wiki/Iran_national_football_team"},"homescorers":"","awayteam":{"text":"Nigeria","href":"http://en.wikipedia.org/wiki/Nigeria_national_football_team"},"awayscorers":"","scoreline":"0–0"},{"hometeam":{"text":"Argentina","href":"http://en.wikipedia.org/wiki/Argentina_national_football_team"},"homescorers":[{"text":"Kolašinac","href":"http://en.wikipedia.org/wiki/Sead_Kola%C5%A1inac"},{"text":"Messi","href":"http://en.wikipedia.org/wiki/Lionel_Messi"}],"awayteam":{"text":"Bosnia and Herzegovina","href":"http://en.wikipedia.org/wiki/Bosnia_and_Herzegovina_national_football_team"},"awayscorers":{"text":"Ibišević","href":"http://en.wikipedia.org/wiki/Vedad_Ibi%C5%A1evi%C4%87"},"scoreline":"2–1"},{"hometeam":{"text":"Argentina","href":"http://en.wikipedia.org/wiki/Argentina_national_football_team"},"homescorers":{"text":"Messi","href":"http://en.wikipedia.org/wiki/Lionel_Messi"},"awayteam":{"text":"Iran","href":"http://en.wikipedia.org/wiki/Iran_national_football_team"},"awayscorers":"","scoreline":"1–0"},{"hometeam":{"text":"Nigeria","href":"http://en.wikipedia.org/wiki/Nigeria_national_football_team"},"homescorers":{"text":"Odemwingie","href":"http://en.wikipedia.org/wiki/Peter_Odemwingie"},"awayteam":{"text":"Bosnia and Herzegovina","href":"http://en.wikipedia.org/wiki/Bosnia_and_Herzegovina_national_football_team"},"awayscorers":"","scoreline":"1–0"},{"hometeam":{"text":"Nigeria","href":"http://en.wikipedia.org/wiki/Nigeria_national_football_team"},"homescorers":{"text":"Musa","href":"http://en.wikipedia.org/wiki/Ahmed_Musa_(footballer)"},"awayteam":{"text":"Argentina","href":"http://en.wikipedia.org/wiki/Argentina_national_football_team"},"awayscorers":[{"text":"Messi","href":"http://en.wikipedia.org/wiki/Lionel_Messi"},{"text":"Rojo","href":"http://en.wikipedia.org/wiki/Marcos_Rojo"}],"scoreline":"2–3"},{"hometeam":{"text":"Bosnia and Herzegovina","href":"http://en.wikipedia.org/wiki/Bosnia_and_Herzegovina_national_football_team"},"homescorers":[{"text":"Džeko","href":"http://en.wikipedia.org/wiki/Edin_D%C5%BEeko"},{"text":"Pjanić","href":"http://en.wikipedia.org/wiki/Miralem_Pjani%C4%87"},{"text":"Vršajević","href":"http://en.wikipedia.org/wiki/Avdija_Vr%C5%A1ajevi%C4%87"}],"awayteam":{"text":"Iran","href":"http://en.wikipedia.org/wiki/Iran_national_football_team"},"awayscorers":{"text":"Ghoochannejhad","href":"http://en.wikipedia.org/wiki/Reza_Ghoochannejhad"},"scoreline":"3–1"},{"hometeam":"","homescorers":"","awayteam":"","awayscorers":"","scoreline":""},{"hometeam":"","homescorers":"","awayteam":"","awayscorers":"","scoreline":""},{"hometeam":{"text":"Germany","href":"http://en.wikipedia.org/wiki/Germany_national_football_team"},"homescorers":[{"text":"Müller","href":"http://en.wikipedia.org/wiki/Thomas_M%C3%BCller"},{"text":"Hummels","href":"http://en.wikipedia.org/wiki/Mats_Hummels"}],"awayteam":{"text":"Portugal","href":"http://en.wikipedia.org/wiki/Portugal_national_football_team"},"awayscorers":"","scoreline":"4–0"},{"hometeam":{"text":"Ghana","href":"http://en.wikipedia.org/wiki/Ghana_national_football_team"},"homescorers":{"text":"A. Ayew","href":"http://en.wikipedia.org/wiki/Andr%C3%A9_Ayew"},"awayteam":{"text":"United States","href":"http://en.wikipedia.org/wiki/United_States_men%27s_national_soccer_team"},"awayscorers":[{"text":"Dempsey","href":"http://en.wikipedia.org/wiki/Clint_Dempsey"},{"text":"Brooks","href":"http://en.wikipedia.org/wiki/John_Anthony_Brooks"}],"scoreline":"1–2"},{"hometeam":{"text":"United States","href":"http://en.wikipedia.org/wiki/United_States_men%27s_national_soccer_team"},"homescorers":"","awayteam":{"text":"Germany","href":"http://en.wikipedia.org/wiki/Germany_national_football_team"},"awayscorers":{"text":"Müller","href":"http://en.wikipedia.org/wiki/Thomas_M%C3%BCller"},"scoreline":"0–1"},{"hometeam":{"text":"Germany","href":"http://en.wikipedia.org/wiki/Germany_national_football_team"},"homescorers":[{"text":"Götze","href":"http://en.wikipedia.org/wiki/Mario_G%C3%B6tze"},{"text":"Klose","href":"http://en.wikipedia.org/wiki/Miroslav_Klose"}],"awayteam":{"text":"Ghana","href":"http://en.wikipedia.org/wiki/Ghana_national_football_team"},"awayscorers":[{"text":"A. Ayew","href":"http://en.wikipedia.org/wiki/Andr%C3%A9_Ayew"},{"text":"Gyan","href":"http://en.wikipedia.org/wiki/Asamoah_Gyan"}],"scoreline":"2–2"},{"hometeam":{"text":"United States","href":"http://en.wikipedia.org/wiki/United_States_men%27s_national_soccer_team"},"homescorers":[{"text":"Jones","href":"http://en.wikipedia.org/wiki/Jermaine_Jones"},{"text":"Dempsey","href":"http://en.wikipedia.org/wiki/Clint_Dempsey"}],"awayteam":{"text":"Portugal","href":"http://en.wikipedia.org/wiki/Portugal_national_football_team"},"awayscorers":[{"text":"Nani","href":"http://en.wikipedia.org/wiki/Nani"},{"text":"Varela","href":"http://en.wikipedia.org/wiki/Silvestre_Varela"}],"scoreline":"2–2"},{"hometeam":{"text":"Portugal","href":"http://en.wikipedia.org/wiki/Portugal_national_football_team"},"homescorers":[{"text":"Boye","href":"http://en.wikipedia.org/wiki/John_Boye"},{"text":"Ronaldo","href":"http://en.wikipedia.org/wiki/Cristiano_Ronaldo"}],"awayteam":{"text":"Ghana","href":"http://en.wikipedia.org/wiki/Ghana_national_football_team"},"awayscorers":{"text":"Gyan","href":"http://en.wikipedia.org/wiki/Asamoah_Gyan"},"scoreline":"2–1"},{"hometeam":"","homescorers":"","awayteam":"","awayscorers":"","scoreline":""},{"hometeam":"","homescorers":"","awayteam":"","awayscorers":"","scoreline":""},{"hometeam":"","homescorers":"","awayteam":"","awayscorers":"","scoreline":""},{"hometeam":{"text":"Belgium","href":"http://en.wikipedia.org/wiki/Belgium_national_football_team"},"homescorers":[{"text":"Fellaini","href":"http://en.wikipedia.org/wiki/Marouane_Fellaini"},{"text":"Mertens","href":"http://en.wikipedia.org/wiki/Dries_Mertens"}],"awayteam":{"text":"Algeria","href":"http://en.wikipedia.org/wiki/Algeria_national_football_team"},"awayscorers":{"text":"Feghouli","href":"http://en.wikipedia.org/wiki/Sofiane_Feghouli"},"scoreline":"2–1"},{"hometeam":{"text":"Russia","href":"http://en.wikipedia.org/wiki/Russia_national_football_team"},"homescorers":{"text":"Kerzhakov","href":"http://en.wikipedia.org/wiki/Aleksandr_Kerzhakov"},"awayteam":{"text":"South Korea","href":"http://en.wikipedia.org/wiki/South_Korea_national_football_team"},"awayscorers":{"text":"Lee Keun-ho","href":"http://en.wikipedia.org/wiki/Lee_Keun-ho"},"scoreline":"1–1"},{"hometeam":{"text":"Belgium","href":"http://en.wikipedia.org/wiki/Belgium_national_football_team"},"homescorers":{"text":"Origi","href":"http://en.wikipedia.org/wiki/Divock_Origi"},"awayteam":{"text":"Russia","href":"http://en.wikipedia.org/wiki/Russia_national_football_team"},"awayscorers":"","scoreline":"1–0"},{"hometeam":{"text":"South Korea","href":"http://en.wikipedia.org/wiki/South_Korea_national_football_team"},"homescorers":"","awayteam":{"text":"Belgium","href":"http://en.wikipedia.org/wiki/Belgium_national_football_team"},"awayscorers":{"text":"Vertonghen","href":"http://en.wikipedia.org/wiki/Jan_Vertonghen"},"scoreline":"0–1"},{"hometeam":{"text":"Algeria","href":"http://en.wikipedia.org/wiki/Algeria_national_football_team"},"homescorers":{"text":"Slimani","href":"http://en.wikipedia.org/wiki/Islam_Slimani"},"awayteam":{"text":"Russia","href":"http://en.wikipedia.org/wiki/Russia_national_football_team"},"awayscorers":{"text":"Kokorin","href":"http://en.wikipedia.org/wiki/Aleksandr_Kokorin"},"scoreline":"1–1"},{"hometeam":{"text":"South Korea","href":"http://en.wikipedia.org/wiki/South_Korea_national_football_team"},"homescorers":[{"text":"Son Heung-min","href":"http://en.wikipedia.org/wiki/Son_Heung-min"},{"text":"Koo Ja-cheol","href":"http://en.wikipedia.org/wiki/Koo_Ja-cheol"}],"awayteam":{"text":"Algeria","href":"http://en.wikipedia.org/wiki/Algeria_national_football_team"},"awayscorers":[{"text":"Slimani","href":"http://en.wikipedia.org/wiki/Islam_Slimani"},{"text":"Halliche","href":"http://en.wikipedia.org/wiki/Rafik_Halliche"},{"text":"Djabou","href":"http://en.wikipedia.org/wiki/Abdelmoumene_Djabou"},{"text":"Brahimi","href":"http://en.wikipedia.org/wiki/Yacine_Brahimi"}],"scoreline":"2–4"},{"hometeam":"","homescorers":"","awayteam":"","awayscorers":"","scoreline":""},{"hometeam":"","homescorers":"","awayteam":"","awayscorers":"","scoreline":""}]}}